{"stage_id": 5001, "start_time": 1605873600, "shift_type": "normal", "end_time": 1606024800, "weapon_list": [1000, 60, 3040, 4010], "rare_weapon": null, "records": {"golden_eggs": {"total": {"id": 670962, "golden_eggs": 173, "power_eggs": 3075, "members": ["2e86f880e0fcdbcb", "5627919bb16897c4", "a0720e1c8cecd9fc", "d455dc3f1f32ce5d"], "water_level": null, "event_type": null}, "no_night_event": {"id": 668150, "golden_eggs": 155, "power_eggs": 4027, "members": ["2e86f880e0fcdbcb", "a0720e1c8cecd9fc", "aae300eb7db4f6dd", "b47e1fd7a7e6feb5"], "water_level": null, "event_type": null}, "waves": [{"id": 671300, "golden_eggs": 62, "power_eggs": 1531, "members": ["2e86f880e0fcdbcb", "5627919bb16897c4", "a0720e1c8cecd9fc", "d455dc3f1f32ce5d"], "water_level": "low", "event_type": "-"}, {"id": 671398, "golden_eggs": 63, "power_eggs": 2713, "members": ["5db950fcf6763803", "759f8285abd07135", "a6698b80745752ab", "daf36b6006b5dae8"], "water_level": "low", "event_type": "cohock-charge"}, {"id": 667692, "golden_eggs": 75, "power_eggs": 1329, "members": ["2e86f880e0fcdbcb", "a0720e1c8cecd9fc", "aae300eb7db4f6dd", "b47e1fd7a7e6feb5"], "water_level": "low", "event_type": "fog"}, {"id": 671395, "golden_eggs": 53, "power_eggs": 908, "members": ["5db950fcf6763803", "759f8285abd07135", "a6698b80745752ab", "daf36b6006b5dae8"], "water_level": "low", "event_type": "the-mothership"}, {"id": 670764, "golden_eggs": 58, "power_eggs": 837, "members": ["2e86f880e0fcdbcb", "5627919bb16897c4", "a0720e1c8cecd9fc", "d455dc3f1f32ce5d"], "water_level": "normal", "event_type": "-"}, {"id": 676246, "golden_eggs": 67, "power_eggs": 711, "members": ["b2845a45750a76c8", "b2da7c8ca0e06fa7", "cde7ed3fa44ad577", "d455dc3f1f32ce5d"], "water_level": "normal", "event_type": "fog"}, {"id": 668368, "golden_eggs": 60, "power_eggs": 1274, "members": ["2e86f880e0fcdbcb", "a0720e1c8cecd9fc", "aae300eb7db4f6dd", "b47e1fd7a7e6feb5"], "water_level": "normal", "event_type": "goldie-seeking"}, {"id": 667606, "golden_eggs": 55, "power_eggs": 1361, "members": ["2e86f880e0fcdbcb", "a0720e1c8cecd9fc", "aae300eb7db4f6dd", "b47e1fd7a7e6feb5"], "water_level": "normal", "event_type": "griller"}, {"id": 670967, "golden_eggs": 53, "power_eggs": 680, "members": ["2e86f880e0fcdbcb", "5627919bb16897c4", "a0720e1c8cecd9fc", "d455dc3f1f32ce5d"], "water_level": "normal", "event_type": "the-mothership"}, {"id": 668370, "golden_eggs": 55, "power_eggs": 2422, "members": ["2e86f880e0fcdbcb", "a0720e1c8cecd9fc", "aae300eb7db4f6dd", "b47e1fd7a7e6feb5"], "water_level": "normal", "event_type": "rush"}, {"id": 671403, "golden_eggs": 59, "power_eggs": 1189, "members": ["5db950fcf6763803", "759f8285abd07135", "a6698b80745752ab", "daf36b6006b5dae8"], "water_level": "high", "event_type": "-"}, {"id": 671396, "golden_eggs": 66, "power_eggs": 1318, "members": ["5db950fcf6763803", "759f8285abd07135", "a6698b80745752ab", "daf36b6006b5dae8"], "water_level": "high", "event_type": "fog"}, {"id": 671288, "golden_eggs": 61, "power_eggs": 2335, "members": ["2e86f880e0fcdbcb", "5627919bb16897c4", "a0720e1c8cecd9fc", "d455dc3f1f32ce5d"], "water_level": "high", "event_type": "goldie-seeking"}, {"id": 667698, "golden_eggs": 75, "power_eggs": 1880, "members": ["2e86f880e0fcdbcb", "a0720e1c8cecd9fc", "aae300eb7db4f6dd", "b47e1fd7a7e6feb5"], "water_level": "high", "event_type": "griller"}, {"id": 671340, "golden_eggs": 49, "power_eggs": 892, "members": ["0207ac94447f2565", "a9bba5aac8f7a5c6", "be75d0713654e1db", "cc0600ce2d5eb64a"], "water_level": "high", "event_type": "the-mothership"}, {"id": 675768, "golden_eggs": 52, "power_eggs": 2912, "members": ["0207ac94447f2565", "1a6c2d45dd7a4d91", "26614a0c758671c3", "5627919bb16897c4"], "water_level": "high", "event_type": "rush"}]}, "power_eggs": {"total": {"id": 668778, "golden_eggs": 106, "power_eggs": 9508, "members": ["0294ff3a62939a7a", "79a113e58a3a01f5", "a68d13676265a1f6", "c67874aa5417835f"], "water_level": null, "event_type": null}, "no_night_event": {"id": 671643, "golden_eggs": 88, "power_eggs": 5271, "members": ["27b31a21fe2725ad", "66ffbce054aa5291", "aa346071b3576101", "d3e54a7476b83d50"], "water_level": null, "event_type": null}, "waves": [{"id": 673490, "golden_eggs": 44, "power_eggs": 1883, "members": ["429721d9d5d3e8d6", "701f07f4f86556c0", "b424ebc250ff85f6", "e6b8a14b7e8a6f88"], "water_level": "low", "event_type": "-"}, {"id": 667841, "golden_eggs": 29, "power_eggs": 3655, "members": ["36d4d8c0560b26b5", "3b631ac4762a51ec", "7cd02833216c0956", "c41a2b3dc64a0bfc"], "water_level": "low", "event_type": "cohock-charge"}, {"id": 670271, "golden_eggs": 36, "power_eggs": 1598, "members": ["3e44c8b5d74a5d37", "a773c9a9c4182410", "ac9b814cf60336e6", "ef41aa181c1d4a72"], "water_level": "low", "event_type": "fog"}, {"id": 679259, "golden_eggs": 24, "power_eggs": 1324, "members": ["2df5c0251486b968", "69b4de95afdad31b", "c7b1a9a810516adf", "dda957f3f544367a"], "water_level": "low", "event_type": "the-mothership"}, {"id": 669361, "golden_eggs": 30, "power_eggs": 1197, "members": ["347b7a5eaaad3728", "4fb8f822a87915ba", "5ed1953630305877", "acd39bd2f16d5012"], "water_level": "normal", "event_type": "-"}, {"id": 668797, "golden_eggs": 27, "power_eggs": 1006, "members": ["0294ff3a62939a7a", "3a36a5ea4d873e1d", "6b5e5da77f561675", "c67874aa5417835f"], "water_level": "normal", "event_type": "fog"}, {"id": 670883, "golden_eggs": 31, "power_eggs": 1730, "members": ["30409f55caa05ed2", "9d102297c9cad94f", "ca318f51a1acc858", "dd84b53a5864e26e"], "water_level": "normal", "event_type": "goldie-seeking"}, {"id": 668966, "golden_eggs": 32, "power_eggs": 1422, "members": ["19353ca34dffb164", "66ffbce054aa5291", "c44aff3b2b42e6d7", "e72db3a8692dcf36"], "water_level": "normal", "event_type": "griller"}, {"id": 670266, "golden_eggs": 32, "power_eggs": 800, "members": ["4c4bbf2edcd86a51", "a773c9a9c4182410", "b9e49bafce4f1dcd", "ef41aa181c1d4a72"], "water_level": "normal", "event_type": "the-mothership"}, {"id": 672272, "golden_eggs": 26, "power_eggs": 2575, "members": ["178332439c5a3b54", "1d00514fed08212e", "52d5c2d24314842a", "6da3bd13cd487eb1"], "water_level": "normal", "event_type": "rush"}, {"id": 671643, "golden_eggs": 27, "power_eggs": 2129, "members": ["27b31a21fe2725ad", "66ffbce054aa5291", "aa346071b3576101", "d3e54a7476b83d50"], "water_level": "high", "event_type": "-"}, {"id": 673484, "golden_eggs": 41, "power_eggs": 1699, "members": ["5fd8e68140b4df00", "701f07f4f86556c0", "b424ebc250ff85f6", "e6b8a14b7e8a6f88"], "water_level": "high", "event_type": "fog"}, {"id": 671288, "golden_eggs": 61, "power_eggs": 2335, "members": ["2e86f880e0fcdbcb", "5627919bb16897c4", "a0720e1c8cecd9fc", "d455dc3f1f32ce5d"], "water_level": "high", "event_type": "goldie-seeking"}, {"id": 667698, "golden_eggs": 75, "power_eggs": 1880, "members": ["2e86f880e0fcdbcb", "a0720e1c8cecd9fc", "aae300eb7db4f6dd", "b47e1fd7a7e6feb5"], "water_level": "high", "event_type": "griller"}, {"id": 672855, "golden_eggs": 31, "power_eggs": 1581, "members": ["6e772b5f16b2715e", "7fd585ca7d4bef1f", "8db26d4c24ee37fd", "f4c9a504b7327d6e"], "water_level": "high", "event_type": "the-mothership"}, {"id": 668263, "golden_eggs": 32, "power_eggs": 3676, "members": ["1a789c82e875701c", "3d4641530ea72a05", "5494cf60c7893cda", "a0afec5709a83a05"], "water_level": "high", "event_type": "rush"}]}}}