{"stage_id": 5000, "salmon_id": 1332324, "shift_type": "normal", "danger_rate": "184.0", "golden_eggs": 98, "power_eggs": 3241, "members": ["35b88c5393d0a90f", "67a5964dedd92579", "91d160aa84e88da6", "dce378d176b4f876"], "start_time": 1622656800, "weapon_list": [6000, 210, 1030, 2010], "wave": [{"event_type": "-", "water_level": "low", "golden_ikura_num": 32, "ikura_num": 1107}, {"event_type": "-", "water_level": "normal", "golden_ikura_num": 28, "ikura_num": 889}, {"event_type": "goldie-seeking", "water_level": "high", "golden_ikura_num": 38, "ikura_num": 1245}]}