{"stage_id": 5003, "salmon_id": 1381808, "shift_type": "normal", "danger_rate": "177.2", "golden_eggs": 94, "power_eggs": 4594, "members": ["3dd4346a74c9979f", "488696bee66075d1", "4d623d75105c4c38", "91d160aa84e88da6"], "start_time": 1624384800, "weapon_list": [210, 20, 4030, 2030], "wave": [{"event_type": "-", "water_level": "normal", "golden_ikura_num": 22, "ikura_num": 893}, {"event_type": "-", "water_level": "high", "golden_ikura_num": 34, "ikura_num": 1184}, {"event_type": "rush", "water_level": "normal", "golden_ikura_num": 38, "ikura_num": 2517}]}