{"stage_id": 5003, "salmon_id": 1580492, "shift_type": "normal", "danger_rate": "176.0", "golden_eggs": 134, "power_eggs": 3237, "members": ["2190d31444d47ae1", "594cb1de24eaeebc", "91d160aa84e88da6", "acdba19922871e89"], "start_time": 1629871200, "weapon_list": [1010, 300, 5010, 2020], "wave": [{"event_type": "-", "water_level": "high", "golden_ikura_num": 42, "ikura_num": 1039}, {"event_type": "-", "water_level": "normal", "golden_ikura_num": 41, "ikura_num": 1052}, {"event_type": "-", "water_level": "low", "golden_ikura_num": 51, "ikura_num": 1146}]}