{"stage_id": 5003, "salmon_id": 1636442, "shift_type": "normal", "danger_rate": "200.0", "golden_eggs": 162, "power_eggs": 3730, "members": ["4e217af8576c7364", "66ffbce054aa5291", "91d160aa84e88da6", "91e9b46b91ad3e3e"], "start_time": 1631275200, "weapon_list": [230, 5000, 4030, 2030], "wave": [{"event_type": "-", "water_level": "normal", "golden_ikura_num": 54, "ikura_num": 1023}, {"event_type": "fog", "water_level": "high", "golden_ikura_num": 61, "ikura_num": 1413}, {"event_type": "-", "water_level": "normal", "golden_ikura_num": 47, "ikura_num": 1294}]}