{"stage_id": 5002, "salmon_id": 762753, "shift_type": "normal", "danger_rate": "137.0", "golden_eggs": 95, "power_eggs": 4350, "members": ["2b468754434aa420", "7cddfe528535b1d0", "91d160aa84e88da6", "ae570b2064d4b4b6"], "start_time": 1608076800, "weapon_list": [310, 1100, 4000, 90], "wave": [{"event_type": "-", "water_level": "normal", "golden_ikura_num": 32, "ikura_num": 744}, {"event_type": "cohock-charge", "water_level": "low", "golden_ikura_num": 23, "ikura_num": 2702}, {"event_type": "-", "water_level": "normal", "golden_ikura_num": 40, "ikura_num": 904}]}