{"stage_id": 5000, "salmon_id": 770976, "shift_type": "normal", "danger_rate": "165.0", "golden_eggs": 89, "power_eggs": 3837, "members": ["3275502be651a37e", "3eb4b581fd87a032", "91d160aa84e88da6", "df919233872f2ed6"], "start_time": 1608379200, "weapon_list": [5010, 300, 210, 2030], "wave": [{"event_type": "goldie-seeking", "water_level": "high", "golden_ikura_num": 24, "ikura_num": 1438}, {"event_type": "-", "water_level": "low", "golden_ikura_num": 35, "ikura_num": 1127}, {"event_type": "-", "water_level": "low", "golden_ikura_num": 30, "ikura_num": 1272}]}