{"stage_id": 5003, "salmon_id": 867146, "shift_type": "normal", "danger_rate": "200.0", "golden_eggs": 144, "power_eggs": 3435, "members": ["36cfe58828c00e79", "6766e82fba200756", "91d160aa84e88da6", "fd40ad818194f896"], "start_time": 1610906400, "weapon_list": [3000, 300, 5020, 4020], "wave": [{"event_type": "-", "water_level": "normal", "golden_ikura_num": 47, "ikura_num": 1055}, {"event_type": "goldie-seeking", "water_level": "normal", "golden_ikura_num": 53, "ikura_num": 1208}, {"event_type": "-", "water_level": "low", "golden_ikura_num": 44, "ikura_num": 1172}]}