{"stage_id": 5000, "salmon_id": 100383, "shift_type": "normal", "danger_rate": "188.4", "golden_eggs": 89, "power_eggs": 2937, "members": ["329c71017c7d59c3", "3f89c3791c43ea57", "739f4a9b8e4d5e30", "b2a6977062baafae"], "start_time": 1583452800, "weapon_list": [310, 6020, 4000, 250], "wave": [{"event_type": "-", "water_level": "normal", "golden_ikura_num": 32, "ikura_num": 884}, {"event_type": "-", "water_level": "normal", "golden_ikura_num": 29, "ikura_num": 887}, {"event_type": "-", "water_level": "low", "golden_ikura_num": 28, "ikura_num": 1166}]}