{"stage_id": 5001, "salmon_id": 115788, "shift_type": "random1", "danger_rate": "200.0", "golden_eggs": 108, "power_eggs": 2571, "members": ["3f89c3791c43ea57", "639e315f7cbfed80", "c49ef327331e1eed", "c7771cbd4d28a02e"], "start_time": 1584705600, "weapon_list": [4040, 5000, 2020, -1], "wave": [{"event_type": "griller", "water_level": "normal", "golden_ikura_num": 33, "ikura_num": 880}, {"event_type": "-", "water_level": "normal", "golden_ikura_num": 35, "ikura_num": 769}, {"event_type": "-", "water_level": "normal", "golden_ikura_num": 40, "ikura_num": 922}]}