{"stage_id": 5000, "salmon_id": 26741, "shift_type": "random1", "danger_rate": "200.0", "golden_eggs": 92, "power_eggs": 4562, "members": ["17fa4a213f7e7bd1", "36cfe58828c00e79", "3f89c3791c43ea57", "fdacccf138ebca81"], "start_time": 1575136800, "weapon_list": [0, 5010, 6010, -1], "wave": [{"event_type": "fog", "water_level": "low", "golden_ikura_num": 43, "ikura_num": 1182}, {"event_type": "-", "water_level": "normal", "golden_ikura_num": 25, "ikura_num": 869}, {"event_type": "cohock-charge", "water_level": "low", "golden_ikura_num": 24, "ikura_num": 2511}]}