{"stage_id": 5000, "salmon_id": 270994, "shift_type": "grizzco", "danger_rate": "200.0", "golden_eggs": 138, "power_eggs": 3929, "members": ["3f89c3791c43ea57", "92d40edaa073b9af", "e0f808422b4acb78", "e66aa5f00f04b990"], "start_time": 1593172800, "weapon_list": [-2, -2, -2, -2], "wave": [{"event_type": "goldie-seeking", "water_level": "normal", "golden_ikura_num": 48, "ikura_num": 1482}, {"event_type": "-", "water_level": "high", "golden_ikura_num": 46, "ikura_num": 1536}, {"event_type": "-", "water_level": "normal", "golden_ikura_num": 44, "ikura_num": 911}]}