{"stage_id": 5000, "salmon_id": 271095, "shift_type": "grizzco", "danger_rate": "200.0", "golden_eggs": 153, "power_eggs": 3609, "members": ["3f89c3791c43ea57", "92d40edaa073b9af", "e0f808422b4acb78", "e66aa5f00f04b990"], "start_time": 1593172800, "weapon_list": [-2, -2, -2, -2], "wave": [{"event_type": "griller", "water_level": "high", "golden_ikura_num": 61, "ikura_num": 1567}, {"event_type": "-", "water_level": "normal", "golden_ikura_num": 49, "ikura_num": 920}, {"event_type": "-", "water_level": "normal", "golden_ikura_num": 43, "ikura_num": 1122}]}