{"stage_id": 5004, "salmon_id": 274074, "shift_type": "normal", "danger_rate": "151.0", "golden_eggs": 73, "power_eggs": 3170, "members": ["11f7bd588ec403fa", "13d7be9253e889e8", "3f89c3791c43ea57", "4524955e5b2687aa"], "start_time": 1593345600, "weapon_list": [310, 300, 230, 4010], "wave": [{"event_type": "-", "water_level": "high", "golden_ikura_num": 25, "ikura_num": 1060}, {"event_type": "-", "water_level": "low", "golden_ikura_num": 22, "ikura_num": 747}, {"event_type": "-", "water_level": "high", "golden_ikura_num": 26, "ikura_num": 1363}]}