{"stage_id": 5004, "salmon_id": 27629, "shift_type": "normal", "danger_rate": "147.0", "golden_eggs": 75, "power_eggs": 2606, "members": ["3f89c3791c43ea57", "4658effdc2c6f4b7", "c51d57d09c4fa8ce", "d696a3cbd07ada26"], "start_time": 1575309600, "weapon_list": [4000, 1030, 80, 2000], "wave": [{"event_type": "-", "water_level": "normal", "golden_ikura_num": 22, "ikura_num": 498}, {"event_type": "cohock-charge", "water_level": "low", "golden_ikura_num": 25, "ikura_num": 1587}, {"event_type": "-", "water_level": "normal", "golden_ikura_num": 28, "ikura_num": 521}]}