{"stage_id": 5004, "salmon_id": 289806, "shift_type": "normal", "danger_rate": "179.0", "golden_eggs": 99, "power_eggs": 5262, "members": ["2a924dd37f9ba2c1", "3f89c3791c43ea57", "9e5ffab5ca10573b", "fdd7e4a1fe702d45"], "start_time": 1594123200, "weapon_list": [60, 6000, 5010, 2010], "wave": [{"event_type": "-", "water_level": "high", "golden_ikura_num": 46, "ikura_num": 1526}, {"event_type": "rush", "water_level": "normal", "golden_ikura_num": 23, "ikura_num": 1631}, {"event_type": "cohock-charge", "water_level": "low", "golden_ikura_num": 30, "ikura_num": 2105}]}