{"stage_id": 5004, "salmon_id": 336778, "shift_type": "random4", "danger_rate": "176.8", "golden_eggs": 87, "power_eggs": 2051, "members": ["23e32d70dedd0c8f", "3d7eab9d9598e504", "3f89c3791c43ea57", "ae570b2064d4b4b6"], "start_time": 1595678400, "weapon_list": [-1, -1, -1, -1], "wave": [{"event_type": "-", "water_level": "normal", "golden_ikura_num": 36, "ikura_num": 691}, {"event_type": "-", "water_level": "normal", "golden_ikura_num": 29, "ikura_num": 750}, {"event_type": "-", "water_level": "normal", "golden_ikura_num": 22, "ikura_num": 610}]}