{"stage_id": 5000, "salmon_id": 36945, "shift_type": "normal", "danger_rate": "150.2", "golden_eggs": 46, "power_eggs": 1944, "members": ["37c85e565754dddf", "3f89c3791c43ea57", "4658effdc2c6f4b7", "967922bbe4650cc8"], "start_time": 1576713600, "weapon_list": [40, 20, 30, 2030], "wave": [{"event_type": "-", "water_level": "normal", "golden_ikura_num": 25, "ikura_num": 841}, {"event_type": "the-mothership", "water_level": "normal", "golden_ikura_num": 18, "ikura_num": 591}, {"event_type": "-", "water_level": "high", "golden_ikura_num": 3, "ikura_num": 512}]}