{"stage_id": 5000, "salmon_id": 397685, "shift_type": "normal", "danger_rate": "119.6", "golden_eggs": 99, "power_eggs": 2803, "members": ["3f89c3791c43ea57", "86add42f24053fae", "934bfc4f8efec898", "ff3ab64b1e4fc693"], "start_time": 1597881600, "weapon_list": [70, 20, 1110, 2010], "wave": [{"event_type": "-", "water_level": "low", "golden_ikura_num": 26, "ikura_num": 913}, {"event_type": "the-mothership", "water_level": "high", "golden_ikura_num": 34, "ikura_num": 827}, {"event_type": "-", "water_level": "normal", "golden_ikura_num": 39, "ikura_num": 1063}]}