{"stage_id": 5004, "salmon_id": 42145, "shift_type": "random1", "danger_rate": "195.4", "golden_eggs": 93, "power_eggs": 1968, "members": ["1eb50dc994d33c5e", "3f89c3791c43ea57", "4658effdc2c6f4b7", "5c73b08340097150"], "start_time": 1577491200, "weapon_list": [20, 4030, 2020, -1], "wave": [{"event_type": "-", "water_level": "normal", "golden_ikura_num": 29, "ikura_num": 577}, {"event_type": "-", "water_level": "normal", "golden_ikura_num": 37, "ikura_num": 675}, {"event_type": "-", "water_level": "normal", "golden_ikura_num": 27, "ikura_num": 716}]}