{"stage_id": 5004, "salmon_id": 42327, "shift_type": "random1", "danger_rate": "197.2", "golden_eggs": 80, "power_eggs": 3197, "members": ["1eb50dc994d33c5e", "200f810670942902", "3f89c3791c43ea57", "4658effdc2c6f4b7"], "start_time": 1577491200, "weapon_list": [20, 4030, 2020, -1], "wave": [{"event_type": "-", "water_level": "normal", "golden_ikura_num": 20, "ikura_num": 469}, {"event_type": "-", "water_level": "normal", "golden_ikura_num": 30, "ikura_num": 682}, {"event_type": "cohock-charge", "water_level": "low", "golden_ikura_num": 30, "ikura_num": 2046}]}