{"stage_id": 5003, "salmon_id": 60648, "shift_type": "random1", "danger_rate": "148.2", "golden_eggs": 100, "power_eggs": 4170, "members": ["282abc69e491d7ba", "3f89c3791c43ea57", "9bcf2983e9b887ba", "fdd7e4a1fe702d45"], "start_time": 1579996800, "weapon_list": [50, 3030, 2000, -1], "wave": [{"event_type": "-", "water_level": "high", "golden_ikura_num": 35, "ikura_num": 1162}, {"event_type": "rush", "water_level": "normal", "golden_ikura_num": 30, "ikura_num": 1919}, {"event_type": "-", "water_level": "normal", "golden_ikura_num": 35, "ikura_num": 1089}]}