{"stage_id": 5003, "salmon_id": 615360, "shift_type": "random1", "danger_rate": "200.0", "golden_eggs": 93, "power_eggs": 3042, "members": ["2b631927ccf9f9d2", "3f89c3791c43ea57", "e3c88a259faf3083", "e6b8a14b7e8a6f88"], "start_time": 1604145600, "weapon_list": [20, 3000, 2000, -1], "wave": [{"event_type": "-", "water_level": "normal", "golden_ikura_num": 31, "ikura_num": 922}, {"event_type": "-", "water_level": "low", "golden_ikura_num": 29, "ikura_num": 1134}, {"event_type": "-", "water_level": "normal", "golden_ikura_num": 33, "ikura_num": 986}]}