{"stage_id": 5000, "salmon_id": 63845, "shift_type": "normal", "danger_rate": "187.4", "golden_eggs": 119, "power_eggs": 3240, "members": ["36cfe58828c00e79", "3f89c3791c43ea57", "50a42f64cc2e41a3", "98befc783a5e8c04"], "start_time": 1580320800, "weapon_list": [30, 5010, 5000, 2020], "wave": [{"event_type": "fog", "water_level": "normal", "golden_ikura_num": 38, "ikura_num": 957}, {"event_type": "-", "water_level": "high", "golden_ikura_num": 41, "ikura_num": 1359}, {"event_type": "-", "water_level": "normal", "golden_ikura_num": 40, "ikura_num": 924}]}