{"stage_id": 5004, "salmon_id": 83235, "shift_type": "normal", "danger_rate": "200.0", "golden_eggs": 126, "power_eggs": 3433, "members": ["36cfe58828c00e79", "3f89c3791c43ea57", "739f4a9b8e4d5e30", "eb087d9428469ad7"], "start_time": 1582200000, "weapon_list": [60, 40, 6000, 2060], "wave": [{"event_type": "-", "water_level": "low", "golden_ikura_num": 41, "ikura_num": 1054}, {"event_type": "the-mothership", "water_level": "normal", "golden_ikura_num": 36, "ikura_num": 514}, {"event_type": "-", "water_level": "high", "golden_ikura_num": 49, "ikura_num": 1865}]}