{"stage_id": 5003, "salmon_id": 906113, "shift_type": "normal", "danger_rate": "200.0", "golden_eggs": 77, "power_eggs": 4643, "members": ["3f89c3791c43ea57", "dd9dd76130623144", "f9acaf6859f3a678", "fc324b472a0dbb78"], "start_time": 1611835200, "weapon_list": [3000, 200, 80, 4010], "wave": [{"event_type": "rush", "water_level": "high", "golden_ikura_num": 27, "ikura_num": 2595}, {"event_type": "-", "water_level": "normal", "golden_ikura_num": 24, "ikura_num": 921}, {"event_type": "-", "water_level": "normal", "golden_ikura_num": 26, "ikura_num": 1127}]}