{"stage_id": 5000, "salmon_id": 99314, "shift_type": "normal", "danger_rate": "161.4", "golden_eggs": 107, "power_eggs": 5203, "members": ["34ae6a4d63f2a6b1", "36cfe58828c00e79", "3f89c3791c43ea57", "76ae46d80b09c980"], "start_time": 1583452800, "weapon_list": [310, 6020, 4000, 250], "wave": [{"event_type": "-", "water_level": "normal", "golden_ikura_num": 35, "ikura_num": 888}, {"event_type": "cohock-charge", "water_level": "low", "golden_ikura_num": 41, "ikura_num": 2125}, {"event_type": "rush", "water_level": "normal", "golden_ikura_num": 31, "ikura_num": 2190}]}