{"stage_id": 5003, "start_time": 1581422400, "shift_type": "normal", "end_time": 1581552000, "weapon_list": [70, 400, 4030, 2020], "rare_weapon": null, "records": {"golden_eggs": {"total": {"id": 75877, "golden_eggs": 167, "power_eggs": 3287, "members": ["0dcabf1aa4e70f2e", "25c2a6a7ec0d8863", "4378ddb86f58882e", "a6698b80745752ab"], "water_level": null, "event_type": null}, "no_night_event": {"id": 75887, "golden_eggs": 154, "power_eggs": 3193, "members": ["0dcabf1aa4e70f2e", "25c2a6a7ec0d8863", "4378ddb86f58882e", "a6698b80745752ab"], "water_level": null, "event_type": null}, "waves": [{"id": 74646, "golden_eggs": 49, "power_eggs": 1042, "members": ["0dcabf1aa4e70f2e", "27b314952c00c7fa", "4378ddb86f58882e", "a6698b80745752ab"], "water_level": "low", "event_type": "-"}, {"id": 75466, "golden_eggs": 43, "power_eggs": 2278, "members": ["73df0d4ea54cfec8", "b9d18a7837890929", "c916c8f25ad70f04", "edef2280a4929461"], "water_level": "low", "event_type": "cohock_charge"}, {"id": 74688, "golden_eggs": 51, "power_eggs": 969, "members": ["0dcabf1aa4e70f2e", "27b314952c00c7fa", "4378ddb86f58882e", "a6698b80745752ab"], "water_level": "low", "event_type": "fog"}, {"id": 75882, "golden_eggs": 59, "power_eggs": 711, "members": ["0dcabf1aa4e70f2e", "25c2a6a7ec0d8863", "4378ddb86f58882e", "a6698b80745752ab"], "water_level": "low", "event_type": "the-mothership"}, {"id": 75892, "golden_eggs": 59, "power_eggs": 1113, "members": ["0dcabf1aa4e70f2e", "25c2a6a7ec0d8863", "4378ddb86f58882e", "a6698b80745752ab"], "water_level": "normal", "event_type": "-"}, {"id": 75470, "golden_eggs": 61, "power_eggs": 1217, "members": ["3163d6b7215630f8", "73df0d4ea54cfec8", "b9d18a7837890929", "c916c8f25ad70f04"], "water_level": "normal", "event_type": "fog"}, {"id": 74649, "golden_eggs": 58, "power_eggs": 1376, "members": ["0dcabf1aa4e70f2e", "27b314952c00c7fa", "4378ddb86f58882e", "a6698b80745752ab"], "water_level": "normal", "event_type": "goldie-seeking"}, {"id": 75885, "golden_eggs": 63, "power_eggs": 1545, "members": ["0dcabf1aa4e70f2e", "25c2a6a7ec0d8863", "4378ddb86f58882e", "a6698b80745752ab"], "water_level": "normal", "event_type": "griller"}, {"id": 74592, "golden_eggs": 50, "power_eggs": 726, "members": ["0dcabf1aa4e70f2e", "27b314952c00c7fa", "4378ddb86f58882e", "a6698b80745752ab"], "water_level": "normal", "event_type": "the-mothership"}, {"id": 75896, "golden_eggs": 53, "power_eggs": 2592, "members": ["0dcabf1aa4e70f2e", "25c2a6a7ec0d8863", "4378ddb86f58882e", "a6698b80745752ab"], "water_level": "normal", "event_type": "rush"}, {"id": 74688, "golden_eggs": 59, "power_eggs": 1383, "members": ["0dcabf1aa4e70f2e", "27b314952c00c7fa", "4378ddb86f58882e", "a6698b80745752ab"], "water_level": "high", "event_type": "-"}, {"id": 75854, "golden_eggs": 60, "power_eggs": 1313, "members": ["0dc491588f58b898", "1a789c82e875701c", "5d8df132398727d5", "fb73614274a86d5a"], "water_level": "high", "event_type": "fog"}, {"id": 74606, "golden_eggs": 53, "power_eggs": 1451, "members": ["05e3b38df6a0271b", "1820db1b8809d042", "66ffbce054aa5291", "a0720e1c8cecd9fc"], "water_level": "high", "event_type": "goldie-seeking"}, {"id": 74519, "golden_eggs": 72, "power_eggs": 1554, "members": ["0dcabf1aa4e70f2e", "27b314952c00c7fa", "4378ddb86f58882e", "a6698b80745752ab"], "water_level": "high", "event_type": "griller"}, {"id": 75897, "golden_eggs": 53, "power_eggs": 715, "members": ["0dcabf1aa4e70f2e", "25c2a6a7ec0d8863", "4378ddb86f58882e", "a6698b80745752ab"], "water_level": "high", "event_type": "the-mothership"}, {"id": 75898, "golden_eggs": 51, "power_eggs": 2884, "members": ["0dcabf1aa4e70f2e", "25c2a6a7ec0d8863", "4378ddb86f58882e", "a6698b80745752ab"], "water_level": "high", "event_type": "rush"}]}, "power_eggs": {"total": {"id": 75901, "golden_eggs": 75, "power_eggs": 5580, "members": ["0dcabf1aa4e70f2e", "25c2a6a7ec0d8863", "4378ddb86f58882e", "a6698b80745752ab"], "water_level": null, "event_type": null}, "no_night_event": {"id": 75730, "golden_eggs": 112, "power_eggs": 3974, "members": ["59216a8d983bb32d", "d9d141d2370d7473", "e5c04df4f1598640", "fcf3ceb9156055b2"], "water_level": null, "event_type": null}, "waves": [{"id": 75729, "golden_eggs": 38, "power_eggs": 1557, "members": ["36e7054f93269304", "976251c238b44c04", "c4ba42b4cf2579cd", "d910b31c07e89b25"], "water_level": "low", "event_type": "-"}, {"id": 75901, "golden_eggs": 21, "power_eggs": 2659, "members": ["0dcabf1aa4e70f2e", "25c2a6a7ec0d8863", "4378ddb86f58882e", "a6698b80745752ab"], "water_level": "low", "event_type": "cohock_charge"}, {"id": 75465, "golden_eggs": 24, "power_eggs": 1236, "members": ["0fb36c81b57090fe", "16fb7fd26e7ebb71", "67250ea276e06603", "75b1d60e4686f1e4"], "water_level": "low", "event_type": "fog"}, {"id": 75933, "golden_eggs": 30, "power_eggs": 864, "members": ["36d4d8c0560b26b5", "4173963603482648", "583095e4123f17bb", "78520bb18f9c7702"], "water_level": "low", "event_type": "the-mothership"}, {"id": 75901, "golden_eggs": 24, "power_eggs": 1441, "members": ["0dcabf1aa4e70f2e", "25c2a6a7ec0d8863", "4378ddb86f58882e", "a6698b80745752ab"], "water_level": "normal", "event_type": "-"}, {"id": 75470, "golden_eggs": 61, "power_eggs": 1217, "members": ["3163d6b7215630f8", "73df0d4ea54cfec8", "b9d18a7837890929", "c916c8f25ad70f04"], "water_level": "normal", "event_type": "fog"}, {"id": 75917, "golden_eggs": 46, "power_eggs": 1418, "members": ["4ecbdbad3b5fce72", "58c3848bb5e712df", "be3d7eebb90b6962", "c7dd13292bc54f33"], "water_level": "normal", "event_type": "goldie-seeking"}, {"id": 75885, "golden_eggs": 63, "power_eggs": 1545, "members": ["0dcabf1aa4e70f2e", "25c2a6a7ec0d8863", "4378ddb86f58882e", "a6698b80745752ab"], "water_level": "normal", "event_type": "griller"}, {"id": 74915, "golden_eggs": 34, "power_eggs": 981, "members": ["0f2975fcdc86585a", "6bcc6fc10e765d46", "9bff325ea58e18ab", "f29d6dc28ccc684f"], "water_level": "normal", "event_type": "the-mothership"}, {"id": 75872, "golden_eggs": 47, "power_eggs": 2635, "members": ["0dcabf1aa4e70f2e", "25c2a6a7ec0d8863", "4378ddb86f58882e", "a6698b80745752ab"], "water_level": "normal", "event_type": "rush"}, {"id": 75395, "golden_eggs": 52, "power_eggs": 1614, "members": ["21a135911bffe005", "4acbb348fbe4ae27", "822e0b2ea85f4a4a", "8dac480cf2028082"], "water_level": "high", "event_type": "-"}, {"id": 75278, "golden_eggs": 35, "power_eggs": 1418, "members": ["2829f366a3e91f2e", "835dffa743851f8e", "a030ffd4f52a7ab1", "d10ba33847f39d81"], "water_level": "high", "event_type": "fog"}, {"id": 74606, "golden_eggs": 53, "power_eggs": 1451, "members": ["05e3b38df6a0271b", "1820db1b8809d042", "66ffbce054aa5291", "a0720e1c8cecd9fc"], "water_level": "high", "event_type": "goldie-seeking"}, {"id": 74590, "golden_eggs": 65, "power_eggs": 1667, "members": ["0dcabf1aa4e70f2e", "27b314952c00c7fa", "4378ddb86f58882e", "a6698b80745752ab"], "water_level": "high", "event_type": "griller"}, {"id": 75074, "golden_eggs": 33, "power_eggs": 810, "members": ["2f52f9aded1d9bd0", "37eba491aaa864c2", "67250ea276e06603", "b2d3d7bc7c873b01"], "water_level": "high", "event_type": "the-mothership"}, {"id": 75898, "golden_eggs": 51, "power_eggs": 2884, "members": ["0dcabf1aa4e70f2e", "25c2a6a7ec0d8863", "4378ddb86f58882e", "a6698b80745752ab"], "water_level": "high", "event_type": "rush"}]}}}