{"stage_id": 5000, "start_time": 1600084800, "shift_type": "normal", "end_time": 1600214400, "weapon_list": [5000, 6000, 1000, 90], "rare_weapon": null, "records": {"golden_eggs": {"total": {"id": 477777, "golden_eggs": 189, "power_eggs": 2769, "members": ["3d647759d2e3b0ee", "5627919bb16897c4", "93a486040cd7b375", "a0720e1c8cecd9fc"], "water_level": null, "event_type": null}, "no_night_event": {"id": 479891, "golden_eggs": 178, "power_eggs": 4783, "members": ["5627919bb16897c4", "a0720e1c8cecd9fc", "a8eebf9c682d5c17", "e59e183bcf4a4e3d"], "water_level": null, "event_type": null}, "waves": [{"id": 477209, "golden_eggs": 68, "power_eggs": 1375, "members": ["3d647759d2e3b0ee", "5627919bb16897c4", "93a486040cd7b375", "a0720e1c8cecd9fc"], "water_level": "low", "event_type": "-"}, {"id": 480940, "golden_eggs": 59, "power_eggs": 2259, "members": ["2325a6845a0e9963", "3bf62ab1a934d7df", "4fc9fa14ec5d06bb", "8d1e28ee239c2f85"], "water_level": "low", "event_type": "cohock-charge"}, {"id": 479547, "golden_eggs": 70, "power_eggs": 1449, "members": ["5627919bb16897c4", "a0720e1c8cecd9fc", "a8eebf9c682d5c17", "e59e183bcf4a4e3d"], "water_level": "low", "event_type": "fog"}, {"id": 479727, "golden_eggs": 58, "power_eggs": 990, "members": ["5627919bb16897c4", "a0720e1c8cecd9fc", "a8eebf9c682d5c17", "e59e183bcf4a4e3d"], "water_level": "low", "event_type": "the-mothership"}, {"id": 478088, "golden_eggs": 65, "power_eggs": 1027, "members": ["788580029fe74552", "93a486040cd7b375", "b47e1fd7a7e6feb5", "d455dc3f1f32ce5d"], "water_level": "normal", "event_type": "-"}, {"id": 477777, "golden_eggs": 82, "power_eggs": 949, "members": ["3d647759d2e3b0ee", "5627919bb16897c4", "93a486040cd7b375", "a0720e1c8cecd9fc"], "water_level": "normal", "event_type": "fog"}, {"id": 479591, "golden_eggs": 63, "power_eggs": 1572, "members": ["2325a6845a0e9963", "3bf62ab1a934d7df", "e0c91c057ba81496", "efae74ec9920c457"], "water_level": "normal", "event_type": "goldie-seeking"}, {"id": 477672, "golden_eggs": 69, "power_eggs": 1449, "members": ["3d647759d2e3b0ee", "5627919bb16897c4", "93a486040cd7b375", "a0720e1c8cecd9fc"], "water_level": "normal", "event_type": "griller"}, {"id": 479547, "golden_eggs": 50, "power_eggs": 865, "members": ["5627919bb16897c4", "a0720e1c8cecd9fc", "a8eebf9c682d5c17", "e59e183bcf4a4e3d"], "water_level": "normal", "event_type": "the-mothership"}, {"id": 479559, "golden_eggs": 61, "power_eggs": 2845, "members": ["5627919bb16897c4", "a0720e1c8cecd9fc", "a8eebf9c682d5c17", "e59e183bcf4a4e3d"], "water_level": "normal", "event_type": "rush"}, {"id": 479649, "golden_eggs": 71, "power_eggs": 1717, "members": ["5627919bb16897c4", "a0720e1c8cecd9fc", "a8eebf9c682d5c17", "e59e183bcf4a4e3d"], "water_level": "high", "event_type": "-"}, {"id": 478585, "golden_eggs": 56, "power_eggs": 1220, "members": ["1cab18851d698762", "56c81d55aefd840f", "9ad0cd0f7b7fe45b", "c7a82deaf895b74d"], "water_level": "high", "event_type": "fog"}, {"id": 479784, "golden_eggs": 62, "power_eggs": 1946, "members": ["5627919bb16897c4", "a0720e1c8cecd9fc", "a8eebf9c682d5c17", "e59e183bcf4a4e3d"], "water_level": "high", "event_type": "goldie-seeking"}, {"id": 479549, "golden_eggs": 83, "power_eggs": 1955, "members": ["5627919bb16897c4", "a0720e1c8cecd9fc", "a8eebf9c682d5c17", "e59e183bcf4a4e3d"], "water_level": "high", "event_type": "griller"}, {"id": 479818, "golden_eggs": 62, "power_eggs": 894, "members": ["5627919bb16897c4", "a0720e1c8cecd9fc", "a8eebf9c682d5c17", "e59e183bcf4a4e3d"], "water_level": "high", "event_type": "the-mothership"}, {"id": 477319, "golden_eggs": 79, "power_eggs": 3240, "members": ["3d647759d2e3b0ee", "5627919bb16897c4", "93a486040cd7b375", "a0720e1c8cecd9fc"], "water_level": "high", "event_type": "rush"}]}, "power_eggs": {"total": {"id": 480422, "golden_eggs": 86, "power_eggs": 9999, "members": ["3d647759d2e3b0ee", "66ffbce054aa5291", "788580029fe74552", "a0720e1c8cecd9fc"], "water_level": null, "event_type": null}, "no_night_event": {"id": 479891, "golden_eggs": 178, "power_eggs": 4783, "members": ["5627919bb16897c4", "a0720e1c8cecd9fc", "a8eebf9c682d5c17", "e59e183bcf4a4e3d"], "water_level": null, "event_type": null}, "waves": [{"id": 479431, "golden_eggs": 36, "power_eggs": 1731, "members": ["3d647759d2e3b0ee", "788580029fe74552", "a0720e1c8cecd9fc", "ae570b2064d4b4b6"], "water_level": "low", "event_type": "-"}, {"id": 480206, "golden_eggs": 36, "power_eggs": 3304, "members": ["421a2013582025d8", "63026357d7250c4d", "eb7345474ab89194", "fdbb31192fb90509"], "water_level": "low", "event_type": "cohock-charge"}, {"id": 479547, "golden_eggs": 70, "power_eggs": 1449, "members": ["5627919bb16897c4", "a0720e1c8cecd9fc", "a8eebf9c682d5c17", "e59e183bcf4a4e3d"], "water_level": "low", "event_type": "fog"}, {"id": 475943, "golden_eggs": 30, "power_eggs": 1339, "members": ["a0720e1c8cecd9fc", "a8eebf9c682d5c17", "b47e1fd7a7e6feb5", "e59e183bcf4a4e3d"], "water_level": "low", "event_type": "the-mothership"}, {"id": 480320, "golden_eggs": 31, "power_eggs": 1383, "members": ["3d647759d2e3b0ee", "66ffbce054aa5291", "788580029fe74552", "a0720e1c8cecd9fc"], "water_level": "normal", "event_type": "-"}, {"id": 480475, "golden_eggs": 48, "power_eggs": 1130, "members": ["936758c9bb670868", "afd758f473ce99f8", "f6b066a64a7a9142", "ff9b2d78c514c4ab"], "water_level": "normal", "event_type": "fog"}, {"id": 480595, "golden_eggs": 47, "power_eggs": 1762, "members": ["5627919bb16897c4", "91e9b46b91ad3e3e", "a0720e1c8cecd9fc", "ac3d5ef080df421b"], "water_level": "normal", "event_type": "goldie-seeking"}, {"id": 479414, "golden_eggs": 65, "power_eggs": 1658, "members": ["2f64b91c4ee5b9a4", "3d647759d2e3b0ee", "66ffbce054aa5291", "f97303bd80834670"], "water_level": "normal", "event_type": "griller"}, {"id": 476664, "golden_eggs": 27, "power_eggs": 1155, "members": ["a0720e1c8cecd9fc", "a8eebf9c682d5c17", "b47e1fd7a7e6feb5", "e59e183bcf4a4e3d"], "water_level": "normal", "event_type": "the-mothership"}, {"id": 480943, "golden_eggs": 44, "power_eggs": 2886, "members": ["2325a6845a0e9963", "3bf62ab1a934d7df", "4fc9fa14ec5d06bb", "8d1e28ee239c2f85"], "water_level": "normal", "event_type": "rush"}, {"id": 481178, "golden_eggs": 51, "power_eggs": 2090, "members": ["10b011a4f7024c08", "61f7af9dfebd8e93", "6aaa30a6e9f4e877", "79848024dadf9610"], "water_level": "high", "event_type": "-"}, {"id": 479406, "golden_eggs": 56, "power_eggs": 1761, "members": ["2f64b91c4ee5b9a4", "3d647759d2e3b0ee", "66ffbce054aa5291", "f97303bd80834670"], "water_level": "high", "event_type": "fog"}, {"id": 480422, "golden_eggs": 1, "power_eggs": 3869, "members": ["3d647759d2e3b0ee", "66ffbce054aa5291", "788580029fe74552", "a0720e1c8cecd9fc"], "water_level": "high", "event_type": "goldie-seeking"}, {"id": 479549, "golden_eggs": 83, "power_eggs": 1955, "members": ["5627919bb16897c4", "a0720e1c8cecd9fc", "a8eebf9c682d5c17", "e59e183bcf4a4e3d"], "water_level": "high", "event_type": "griller"}, {"id": 477927, "golden_eggs": 27, "power_eggs": 1911, "members": ["2b42bade7cce2913", "4c4c0f9d9a496f91", "7c331ba2fff80f9f", "cf8bece8db4121c5"], "water_level": "high", "event_type": "the-mothership"}, {"id": 479980, "golden_eggs": 61, "power_eggs": 3383, "members": ["3d647759d2e3b0ee", "788580029fe74552", "a0720e1c8cecd9fc", "ae570b2064d4b4b6"], "water_level": "high", "event_type": "rush"}]}}}