{"stage_id": 5000, "start_time": 1619049600, "shift_type": "normal", "end_time": 1619179200, "weapon_list": [1100, 5030, 50, 2030], "rare_weapon": null, "records": {"golden_eggs": {"total": {"id": 1214193, "golden_eggs": 155, "power_eggs": 3842, "members": ["009ad1b6680b91a3", "96a6ed3f16adf315", "b47e1fd7a7e6feb5", "d455dc3f1f32ce5d"], "water_level": null, "event_type": null}, "no_night_event": {"id": 1214194, "golden_eggs": 149, "power_eggs": 2774, "members": ["009ad1b6680b91a3", "96a6ed3f16adf315", "b47e1fd7a7e6feb5", "d455dc3f1f32ce5d"], "water_level": null, "event_type": null}, "waves": [{"id": 1212622, "golden_eggs": 54, "power_eggs": 1172, "members": ["184f1cde2eb848ab", "2a9e24fe76b8cc69", "372dc4a47a4beed8", "73df0d4ea54cfec8"], "water_level": "low", "event_type": "-"}, {"id": 1214217, "golden_eggs": 56, "power_eggs": 2076, "members": ["009ad1b6680b91a3", "96a6ed3f16adf315", "b47e1fd7a7e6feb5", "d455dc3f1f32ce5d"], "water_level": "low", "event_type": "cohock-charge"}, {"id": 1214060, "golden_eggs": 54, "power_eggs": 1200, "members": ["084c8410a06b7115", "2df5c0251486b968", "87f77c7094d7a606", "9e0808cbde3638ef"], "water_level": "low", "event_type": "fog"}, {"id": 1213121, "golden_eggs": 42, "power_eggs": 762, "members": ["3b812b156501787f", "5377b41b14ce228c", "a4195f722cee4e72", "f7f507a43360f926"], "water_level": "low", "event_type": "the-mothership"}, {"id": 1214223, "golden_eggs": 60, "power_eggs": 965, "members": ["009ad1b6680b91a3", "96a6ed3f16adf315", "b47e1fd7a7e6feb5", "d455dc3f1f32ce5d"], "water_level": "normal", "event_type": "-"}, {"id": 1211947, "golden_eggs": 56, "power_eggs": 888, "members": ["05dc821a11044490", "08f0842c3f6a27fa", "8693b36d8d6036c6", "fc93595c6ab4f07e"], "water_level": "normal", "event_type": "fog"}, {"id": 1213179, "golden_eggs": 39, "power_eggs": 821, "members": ["187d9d4f34632446", "4c00c7b4ac61a3a1", "e2b08cedff836116", "f0472de9fc00d7fd"], "water_level": "normal", "event_type": "goldie-seeking"}, {"id": 1214197, "golden_eggs": 55, "power_eggs": 1340, "members": ["009ad1b6680b91a3", "96a6ed3f16adf315", "b47e1fd7a7e6feb5", "d455dc3f1f32ce5d"], "water_level": "normal", "event_type": "griller"}, {"id": 1214425, "golden_eggs": 43, "power_eggs": 643, "members": ["21d007ba05db6a54", "8c13ff33dd0b3800", "ba7177645da2df59", "f1128afadd8827f1"], "water_level": "normal", "event_type": "the-mothership"}, {"id": 1212627, "golden_eggs": 41, "power_eggs": 2379, "members": ["2a9e24fe76b8cc69", "372dc4a47a4beed8", "73df0d4ea54cfec8", "ad404b01d9297806"], "water_level": "normal", "event_type": "rush"}, {"id": 1214185, "golden_eggs": 54, "power_eggs": 1340, "members": ["009ad1b6680b91a3", "96a6ed3f16adf315", "b47e1fd7a7e6feb5", "d455dc3f1f32ce5d"], "water_level": "high", "event_type": "-"}, {"id": 1219585, "golden_eggs": 48, "power_eggs": 1380, "members": ["0498104e1ac35ad1", "227e89ca979963a5", "af4b24958d0ce03d", "f99c62afe7574d77"], "water_level": "high", "event_type": "fog"}, {"id": 1214493, "golden_eggs": 40, "power_eggs": 1208, "members": ["33e5d419da1585dc", "72a09a79743ddd7e", "7cb19e2ba720cd3c", "894f156f018cb703"], "water_level": "high", "event_type": "goldie-seeking"}, {"id": 1214193, "golden_eggs": 65, "power_eggs": 1568, "members": ["009ad1b6680b91a3", "96a6ed3f16adf315", "b47e1fd7a7e6feb5", "d455dc3f1f32ce5d"], "water_level": "high", "event_type": "griller"}, {"id": 1214186, "golden_eggs": 47, "power_eggs": 1182, "members": ["009ad1b6680b91a3", "96a6ed3f16adf315", "b47e1fd7a7e6feb5", "d455dc3f1f32ce5d"], "water_level": "high", "event_type": "the-mothership"}, {"id": 1214793, "golden_eggs": 44, "power_eggs": 2462, "members": ["4c00c7b4ac61a3a1", "7c331ba2fff80f9f", "7d8f3a876a392dd2", "91e9b46b91ad3e3e"], "water_level": "high", "event_type": "rush"}]}, "power_eggs": {"total": {"id": 1212732, "golden_eggs": 122, "power_eggs": 6746, "members": ["5c85a68f5a1f727b", "5db950fcf6763803", "a6698b80745752ab", "aa4fef305a92d234"], "water_level": null, "event_type": null}, "no_night_event": {"id": 1216324, "golden_eggs": 125, "power_eggs": 4423, "members": ["2524ddf1b3380d23", "a5cbc99a1bf850c2", "f281414ae53c5278", "f8c9a9fdc1be4706"], "water_level": null, "event_type": null}, "waves": [{"id": 1211554, "golden_eggs": 37, "power_eggs": 1648, "members": ["0fc55140cd215f52", "45c10811bbeabb49", "a773c9a9c4182410", "c063c761e2baa9f9"], "water_level": "low", "event_type": "-"}, {"id": 1214122, "golden_eggs": 28, "power_eggs": 3350, "members": ["4d4751ef63e5308a", "80f5158dc430c0e4", "8222ac6741de27f2", "992c5c374ae1b48a"], "water_level": "low", "event_type": "cohock-charge"}, {"id": 1214554, "golden_eggs": 39, "power_eggs": 1334, "members": ["06c67b2444620bf8", "5c6a8341d972bb09", "b9f9b550dc318141", "e9fa4f69d4bdc4b4"], "water_level": "low", "event_type": "fog"}, {"id": 1213979, "golden_eggs": 22, "power_eggs": 957, "members": ["20c5e9e5c0465ccc", "b4d0fe7b685d6e00", "e01454f299faa30a", "f825e355e3d17aa5"], "water_level": "low", "event_type": "the-mothership"}, {"id": 1212033, "golden_eggs": 38, "power_eggs": 1240, "members": ["163a0ddbb84be0d9", "40cb4494bdd6de02", "768bed951fc94244", "86349daa4010a8f0"], "water_level": "normal", "event_type": "-"}, {"id": 1212981, "golden_eggs": 43, "power_eggs": 1120, "members": ["0f4f0ee24a4e100d", "a7830bc1bff02ed8", "cce9eec105d8f1c4", "f54fde355a137044"], "water_level": "normal", "event_type": "fog"}, {"id": 1212985, "golden_eggs": 23, "power_eggs": 1281, "members": ["0f4f0ee24a4e100d", "4ae1478b10de86ad", "9383c9d8b795e10d", "a99354e87c019679"], "water_level": "normal", "event_type": "goldie-seeking"}, {"id": 1213289, "golden_eggs": 43, "power_eggs": 1533, "members": ["0f8df4e3f34832fc", "36e7b69661623da2", "52d87d1123dd8f8d", "b7d9be77340d655b"], "water_level": "normal", "event_type": "griller"}, {"id": 1213296, "golden_eggs": 32, "power_eggs": 850, "members": ["230c5fc4190ff8ee", "52d87d1123dd8f8d", "7468dec94268c0ab", "b7d9be77340d655b"], "water_level": "normal", "event_type": "the-mothership"}, {"id": 1214593, "golden_eggs": 36, "power_eggs": 2409, "members": ["2da02f4acf9dccfe", "481e342e74b6aa09", "64276aef25fb832d", "9019e949388fd0f4"], "water_level": "normal", "event_type": "rush"}, {"id": 1214695, "golden_eggs": 41, "power_eggs": 1948, "members": ["8e808722a12442de", "da43e7ed9738a42e", "dc090b23cdd0d66a", "f0f38a8a3a73f467"], "water_level": "high", "event_type": "-"}, {"id": 1213005, "golden_eggs": 32, "power_eggs": 1483, "members": ["3a4bfb8970e163fc", "3a4c47e13084c9b8", "5472da4dc674f569", "be75d0713654e1db"], "water_level": "high", "event_type": "fog"}, {"id": 1214439, "golden_eggs": 25, "power_eggs": 1749, "members": ["0af0a4b88cef2bf9", "5ff50a31d33c35c7", "cdd937dd9fad6aed", "d2cee920ec7ab95e"], "water_level": "high", "event_type": "goldie-seeking"}, {"id": 1214190, "golden_eggs": 59, "power_eggs": 1702, "members": ["009ad1b6680b91a3", "96a6ed3f16adf315", "b47e1fd7a7e6feb5", "d455dc3f1f32ce5d"], "water_level": "high", "event_type": "griller"}, {"id": 1218651, "golden_eggs": 39, "power_eggs": 1314, "members": ["3f328f07c7397771", "62a21531f4a798d8", "8f50e3894e7bda46", "bdf9d25e874a4216"], "water_level": "high", "event_type": "the-mothership"}, {"id": 1212732, "golden_eggs": 36, "power_eggs": 2918, "members": ["5c85a68f5a1f727b", "5db950fcf6763803", "a6698b80745752ab", "aa4fef305a92d234"], "water_level": "high", "event_type": "rush"}]}}}