{"stage_id": 5000, "start_time": 1632528000, "shift_type": "normal", "end_time": 1632679200, "weapon_list": [5030, 200, 1100, 90], "rare_weapon": null, "records": {"golden_eggs": {"total": {"id": 1686640, "golden_eggs": 179, "power_eggs": 2703, "members": ["4e217af8576c7364", "5db950fcf6763803", "701f07f4f86556c0", "a6698b80745752ab"], "water_level": null, "event_type": null}, "no_night_event": {"id": 1689205, "golden_eggs": 151, "power_eggs": 3033, "members": ["0fc55140cd215f52", "2da02f4acf9dccfe", "5db950fcf6763803", "a6698b80745752ab"], "water_level": null, "event_type": null}, "waves": [{"id": 1689374, "golden_eggs": 64, "power_eggs": 1434, "members": ["0fc55140cd215f52", "2da02f4acf9dccfe", "5db950fcf6763803", "a6698b80745752ab"], "water_level": "low", "event_type": "-"}, {"id": 1686751, "golden_eggs": 58, "power_eggs": 1927, "members": ["4e217af8576c7364", "5db950fcf6763803", "701f07f4f86556c0", "a6698b80745752ab"], "water_level": "low", "event_type": "cohock_charge"}, {"id": 1685446, "golden_eggs": 60, "power_eggs": 1185, "members": ["0fdf5740391de473", "12b74ecd32f8021e", "4ba05ddb358eab5e", "7bb2b331e766b198"], "water_level": "low", "event_type": "fog"}, {"id": 1686640, "golden_eggs": 61, "power_eggs": 873, "members": ["4e217af8576c7364", "5db950fcf6763803", "701f07f4f86556c0", "a6698b80745752ab"], "water_level": "low", "event_type": "the-mothership"}, {"id": 1686657, "golden_eggs": 56, "power_eggs": 1024, "members": ["4e217af8576c7364", "5db950fcf6763803", "701f07f4f86556c0", "a6698b80745752ab"], "water_level": "normal", "event_type": "-"}, {"id": 1686640, "golden_eggs": 70, "power_eggs": 1037, "members": ["4e217af8576c7364", "5db950fcf6763803", "701f07f4f86556c0", "a6698b80745752ab"], "water_level": "normal", "event_type": "fog"}, {"id": 1689199, "golden_eggs": 52, "power_eggs": 963, "members": ["0fc55140cd215f52", "2da02f4acf9dccfe", "5db950fcf6763803", "a6698b80745752ab"], "water_level": "normal", "event_type": "goldie-seeking"}, {"id": 1687265, "golden_eggs": 60, "power_eggs": 1531, "members": ["0fc55140cd215f52", "2da02f4acf9dccfe", "991bf232e9a2eabc", "a6698b80745752ab"], "water_level": "normal", "event_type": "griller"}, {"id": 1686749, "golden_eggs": 45, "power_eggs": 901, "members": ["4e217af8576c7364", "5db950fcf6763803", "701f07f4f86556c0", "a6698b80745752ab"], "water_level": "normal", "event_type": "the-mothership"}, {"id": 1686387, "golden_eggs": 60, "power_eggs": 2386, "members": ["5db950fcf6763803", "701f07f4f86556c0", "a40245a8a0b8624a", "a6698b80745752ab"], "water_level": "normal", "event_type": "rush"}, {"id": 1689195, "golden_eggs": 57, "power_eggs": 1264, "members": ["0fc55140cd215f52", "2da02f4acf9dccfe", "5db950fcf6763803", "a6698b80745752ab"], "water_level": "high", "event_type": "-"}, {"id": 1691322, "golden_eggs": 72, "power_eggs": 1546, "members": ["4e217af8576c7364", "5db950fcf6763803", "7c331ba2fff80f9f", "a6698b80745752ab"], "water_level": "high", "event_type": "fog"}, {"id": 1687961, "golden_eggs": 46, "power_eggs": 1142, "members": ["54308dad2795feb1", "8a191da39e80c9b5", "c8c5695033b83331", "f4f75c4abd84644a"], "water_level": "high", "event_type": "goldie-seeking"}, {"id": 1691318, "golden_eggs": 64, "power_eggs": 1586, "members": ["4e217af8576c7364", "5db950fcf6763803", "7c331ba2fff80f9f", "a6698b80745752ab"], "water_level": "high", "event_type": "griller"}, {"id": 1689207, "golden_eggs": 52, "power_eggs": 929, "members": ["0fc55140cd215f52", "2da02f4acf9dccfe", "5db950fcf6763803", "a6698b80745752ab"], "water_level": "high", "event_type": "the-mothership"}, {"id": 1691324, "golden_eggs": 71, "power_eggs": 3282, "members": ["4e217af8576c7364", "5db950fcf6763803", "7c331ba2fff80f9f", "a6698b80745752ab"], "water_level": "high", "event_type": "rush"}]}, "power_eggs": {"total": {"id": 1687921, "golden_eggs": 88, "power_eggs": 6836, "members": ["09ae6b135a5a4bef", "175c732116e152af", "4b8bb6d3674ffc5f", "7d2fee8c0305fde8"], "water_level": null, "event_type": null}, "no_night_event": {"id": 1690079, "golden_eggs": 101, "power_eggs": 4635, "members": ["0fc55140cd215f52", "34bf5996648e5884", "64817001dda95655", "65f5fcfdc307197b"], "water_level": null, "event_type": null}, "waves": [{"id": 1692227, "golden_eggs": 36, "power_eggs": 1743, "members": ["178332439c5a3b54", "250d09d5cc6c6819", "991bf232e9a2eabc", "db9c0046af688330"], "water_level": "low", "event_type": "-"}, {"id": 1696433, "golden_eggs": 30, "power_eggs": 3386, "members": ["0230b2d3e264a9ed", "2ae4942bf95048b4", "60068f17dad68ee4", "f35703d4b7dbc851"], "water_level": "low", "event_type": "cohock_charge"}, {"id": 1689192, "golden_eggs": 45, "power_eggs": 1360, "members": ["0fc55140cd215f52", "2da02f4acf9dccfe", "5db950fcf6763803", "a6698b80745752ab"], "water_level": "low", "event_type": "fog"}, {"id": 1691330, "golden_eggs": 53, "power_eggs": 1037, "members": ["4e217af8576c7364", "5db950fcf6763803", "7c331ba2fff80f9f", "a6698b80745752ab"], "water_level": "low", "event_type": "the-mothership"}, {"id": 1687477, "golden_eggs": 38, "power_eggs": 1345, "members": ["3e9e064eef572c34", "4711da42ac9cc098", "556349dfe7e81df4", "ce5382ce81c86c5d"], "water_level": "normal", "event_type": "-"}, {"id": 1689633, "golden_eggs": 53, "power_eggs": 1114, "members": ["2524ddf1b3380d23", "d8d821aa9752db5f", "e5483de168532555", "f8387d587288e90b"], "water_level": "normal", "event_type": "fog"}, {"id": 1686751, "golden_eggs": 40, "power_eggs": 1529, "members": ["4e217af8576c7364", "5db950fcf6763803", "701f07f4f86556c0", "a6698b80745752ab"], "water_level": "normal", "event_type": "goldie-seeking"}, {"id": 1688047, "golden_eggs": 49, "power_eggs": 1589, "members": ["374a375001d4a00c", "3ccf1b9164617e3e", "d0490edd4aa34d95", "d570978b18c704d7"], "water_level": "normal", "event_type": "griller"}, {"id": 1696164, "golden_eggs": 40, "power_eggs": 944, "members": ["050a5b516d02b341", "7d2fee8c0305fde8", "b500536d6eb7f2c2", "cc467d828af4e9be"], "water_level": "normal", "event_type": "the-mothership"}, {"id": 1686639, "golden_eggs": 58, "power_eggs": 2671, "members": ["4e217af8576c7364", "5db950fcf6763803", "701f07f4f86556c0", "a6698b80745752ab"], "water_level": "normal", "event_type": "rush"}, {"id": 1690078, "golden_eggs": 28, "power_eggs": 1991, "members": ["0fc55140cd215f52", "262efda1b73507fc", "588ed60257069ff2", "65f5fcfdc307197b"], "water_level": "high", "event_type": "-"}, {"id": 1690404, "golden_eggs": 55, "power_eggs": 1579, "members": ["390e21f636e0dc6b", "d8d821aa9752db5f", "e5483de168532555", "fc93595c6ab4f07e"], "water_level": "high", "event_type": "fog"}, {"id": 1687903, "golden_eggs": 15, "power_eggs": 2034, "members": ["09ae6b135a5a4bef", "175c732116e152af", "4b8bb6d3674ffc5f", "8272881cd2bf5cab"], "water_level": "high", "event_type": "goldie-seeking"}, {"id": 1691224, "golden_eggs": 50, "power_eggs": 1985, "members": ["4597252834da03b5", "5c9479df044bde67", "cf6c5715650e2a21", "eb7345474ab89194"], "water_level": "high", "event_type": "griller"}, {"id": 1691099, "golden_eggs": 29, "power_eggs": 1516, "members": ["34b3035ef8570554", "c469dde7a9f166df", "c71883bc86d6c0a0", "d895026a39177499"], "water_level": "high", "event_type": "the-mothership"}, {"id": 1691324, "golden_eggs": 71, "power_eggs": 3282, "members": ["4e217af8576c7364", "5db950fcf6763803", "7c331ba2fff80f9f", "a6698b80745752ab"], "water_level": "high", "event_type": "rush"}]}}}